LICENSE
README.md
setup.py
medcam/__init__.py
medcam/medcam.py
medcam/medcam_inject.py
medcam/medcam_utils.py
medcam/backends/__init__.py
medcam/backends/base.py
medcam/backends/grad_cam.py
medcam/backends/grad_cam_pp.py
medcam/backends/guided_backpropagation.py
medcam/backends/guided_grad_cam.py
medcam/evaluation/__init__.py
medcam/evaluation/evaluation_utils.py
medcam/evaluation/evaluator.py
medcamEditedbyFiras.egg-info/PKG-INFO
medcamEditedbyFiras.egg-info/SOURCES.txt
medcamEditedbyFiras.egg-info/dependency_links.txt
medcamEditedbyFiras.egg-info/requires.txt
medcamEditedbyFiras.egg-info/top_level.txt
tests/__init__.py
tests/test_classification/__init__.py
tests/test_classification/resnet_test.py
tests/test_segmentation/__init__.py
tests/test_segmentation/unet_seg_dataset.py
tests/test_segmentation/unet_seg_test.py